nostalgia_chrome/__init__.py
nostalgia_chrome/__main__.py
nostalgia_chrome/store_backup.py
nostalgia_chrome/utils.py
nostalgia_chrome/server/__init__.py
nostalgia_chrome/server/app.py
nostalgia_chrome/server/cors.py
nostalgia_chrome/server/utils.py
nostalgia_chrome-0.0.24.dist-info/METADATA
nostalgia_chrome-0.0.24.dist-info/WHEEL
nostalgia_chrome-0.0.24.dist-info/entry_points.txt
nostalgia_chrome-0.0.24.dist-info/top_level.txt
nostalgia_chrome-0.0.24.dist-info/RECORD
