Metadata-Version: 2.1
Name: nostalgia-chrome
Version: 0.0.24
Summary: Self tracking your online life!
Home-page: https://github.com/nostalgia-dev/nostalgia_chrome
Author: Pascal van Kooten
Author-email: kootenpv@gmail.com
License: MIT
Platform: any
Classifier: Environment :: Console
Classifier: Intended Audience :: Developers
Classifier: License :: OSI Approved :: MIT License
Classifier: Operating System :: Microsoft
Classifier: Operating System :: MacOS :: MacOS X
Classifier: Operating System :: Unix
Classifier: Operating System :: POSIX
Classifier: Programming Language :: Python
Classifier: Programming Language :: Python :: 3
Classifier: Programming Language :: Python :: 3.4
Classifier: Programming Language :: Python :: 3.5
Classifier: Programming Language :: Python :: 3.6
Classifier: Programming Language :: Python :: 3.7
Classifier: Topic :: Software Development
Classifier: Topic :: Software Development :: Libraries :: Python Modules
Classifier: Topic :: Utilities
Requires-Dist: lxml
Requires-Dist: flask
Requires-Dist: fire
Requires-Dist: bs4
Requires-Dist: just
